batchkit/__init__.py
batchkit/apiserver.py
batchkit/batch_config.py
batchkit/batch_request.py
batchkit/batch_status.py
batchkit/client.py
batchkit/constants.py
batchkit/endpoint_config.py
batchkit/endpoint_manager.py
batchkit/endpoint_status.py
batchkit/handlers.py
batchkit/logger.py
batchkit/orchestrator.py
batchkit/run_summarizer.py
batchkit/utils.py
batchkit/work_item.py
batchkit/work_item_processor.py
batchkit_examples/__init__.py
batchkit_examples/speech_sdk/__init__.py
batchkit_examples/speech_sdk/audio.py
batchkit_examples/speech_sdk/batch_config.py
batchkit_examples/speech_sdk/batch_request.py
batchkit_examples/speech_sdk/endpoint_status.py
batchkit_examples/speech_sdk/parser.py
batchkit_examples/speech_sdk/recognize.py
batchkit_examples/speech_sdk/run_summarizer.py
batchkit_examples/speech_sdk/work_item.py
batchkit_examples/speech_sdk/work_item_processor.py
batchkit_examples/speech_sdk/lang_id/__init__.py
batchkit_examples/speech_sdk/lang_id/batch_config.py
batchkit_examples/speech_sdk/lang_id/batch_request.py
batchkit_examples/speech_sdk/lang_id/classify.py
batchkit_examples/speech_sdk/lang_id/endpoint_status.py
batchkit_examples/speech_sdk/lang_id/run_summarizer.py
batchkit_examples/speech_sdk/lang_id/work_item.py
batchkit_examples/speech_sdk/lang_id/work_item_processor.py
batchkit_examples/speech_sdk/multilanguage/__init__.py
batchkit_examples/speech_sdk/multilanguage/stage.py
batchkit_examples/speech_sdk/multilanguage/unified_run_summarizer.py
batchkit-0.10.4.dist-info/LICENSE
batchkit-0.10.4.dist-info/METADATA
batchkit-0.10.4.dist-info/WHEEL
batchkit-0.10.4.dist-info/top_level.txt
batchkit-0.10.4.dist-info/RECORD
