Metadata-Version: 2.1
Name: batchkit
Version: 0.10.4
Summary: Generic batch processing framework for managing the orchestration, dispatch, fault tolerance, and monitoring of arbitrary work items against many endpoints. Extensible via dependency injection.
Home-page: https://github.com/microsoft/batch-processing-kit
Author: Microsoft Azure
Author-email: andwald@microsoft.com
License: MIT
Platform: UNKNOWN
Classifier: Programming Language :: Python :: 3
Classifier: License :: OSI Approved :: MIT License
Classifier: Operating System :: POSIX :: Linux
Requires-Python: >=3.6
License-File: LICENSE
Requires-Dist: requests (>=2.27.1)
Requires-Dist: Cerberus (>=1.3.5)
Requires-Dist: deepdiff (>=7.0.1)
Requires-Dist: PyYAML (>=6.0.1)
Requires-Dist: mock (>=5.1.0)
Requires-Dist: Flask (>=3.0.3)
Requires-Dist: jsonpickle (>=3.2.1)
Requires-Dist: requests (>=2.32.3)
Requires-Dist: psutil (>=5.9.8)
Requires-Dist: Werkzeug (>=3.0.3)
Requires-Dist: pyinotify (~=0.9.6) ; sys_platform != "win32"
